schedpy/__init__.py
schedpy/config.py
schedpy/job.py
schedpy/schedule.py
schedpy/utils.py
schedpy-0.1.0.dist-info/LICENSE
schedpy-0.1.0.dist-info/METADATA
schedpy-0.1.0.dist-info/WHEEL
schedpy-0.1.0.dist-info/top_level.txt
schedpy-0.1.0.dist-info/RECORD
