Metadata-Version: 2.1
Name: schedpy
Version: 0.1.0
Summary: A cron or job scheduler in python
Home-page: https://github.com/schedpy/schedpy
Author: Abdullah Javed Nesar
Author-email: abduljaved1994@gmail.com
License: UNKNOWN
Platform: UNKNOWN
Classifier: Programming Language :: Python :: 3
Classifier: License :: OSI Approved :: MIT License
Classifier: Operating System :: OS Independent
Requires-Python: >=3.6
